graphapi/__init__.py
graphapi/auth.py
MicrosoftGraphAPI-0.0.3.dist-info/LICENSE
MicrosoftGraphAPI-0.0.3.dist-info/METADATA
MicrosoftGraphAPI-0.0.3.dist-info/WHEEL
MicrosoftGraphAPI-0.0.3.dist-info/top_level.txt
MicrosoftGraphAPI-0.0.3.dist-info/RECORD
