Metadata-Version: 2.1
Name: MicrosoftGraphAPI
Version: 0.0.3
Summary: A Python package to interact with the Microsoft Graph API
Home-page: https://www.adgstudios.co.za
Author: Ashlin Darius Govindasamy
Author-email: adg@adgstudios.co.za
License: MIT
Platform: UNKNOWN
Classifier: Programming Language :: Python :: 3
Classifier: License :: OSI Approved :: MIT License
Classifier: Operating System :: OS Independent
Requires-Dist: requests
Requires-Dist: pandas
Requires-Dist: msal
